[
    {
        "id": 1,
        "nome":"Rosa Amazônica",
        "preco":"197,00",
        "tipo":"saude",
        "img":"../../public/images/produtos-femininos/rosa-amazonica.webp",
        "descricao":"1 pote",
        "conteudo":"1 pote",
        "link":"https://ev.braip.com/ref?pl=plazl6do&ck=chezlmgr&af=afi4vy6870"
    },
    {
        "id": 2,
        "nome":"Life Detox",
        "preco":"60,90",
        "tipo":"saude",
        "img":"../../public/images/lift_detox_principal.webp",
        "img1":["../../public/images/lift_detox_1_unidade.webp","../../public/images/lift_detox_2_unidaades.jpg"],
        "descricao":"descricao",
        "conteudo":"sdsad a da da da dad asdds",
        "link":"https://ev.braip.com/ref?pl=plagjyq8&ck=chew8wl8&af=afiydz1xz2 "
    }
]